logthon/__init__.py
logthon/logthon.py
tests/__init__.py
tests/test_logthon.py
logthon-2.5.0.dist-info/LICENSE
logthon-2.5.0.dist-info/METADATA
logthon-2.5.0.dist-info/WHEEL
logthon-2.5.0.dist-info/top_level.txt
logthon-2.5.0.dist-info/RECORD
