Metadata-Version: 2.1
Name: logthon
Version: 2.5.0
Summary: A simple logger for Python
Home-page: https://github.com/mastrobirraio/logthon
Author: Giuseppe "mastrobirraio" Matranga
Author-email: matrangagiuseppe99@gmail.com
Maintainer: Giuseppe "mastrobirraio" Matranga
License: GPLv3
Keywords: log logger logging logthon ansi crossplatform xplatform
Platform: UNKNOWN
Classifier: License :: OSI Approved :: GNU General Public License v3 (GPLv3)
Classifier: Operating System :: OS Independent
Classifier: Environment :: Console
Classifier: Intended Audience :: Developers
Classifier: Programming Language :: Python
Classifier: Programming Language :: Python :: 2.7
Classifier: Programming Language :: Python :: 3
Classifier: Programming Language :: Python :: 3.0
Classifier: Programming Language :: Python :: 3.1
Classifier: Programming Language :: Python :: 3.2
Classifier: Programming Language :: Python :: 3.3
Classifier: Programming Language :: Python :: 3.4
Classifier: Programming Language :: Python :: 3.5
Classifier: Programming Language :: Python :: 3.6
Classifier: Programming Language :: Python :: 3.7
Classifier: Programming Language :: Python :: 3.8
Classifier: Programming Language :: Python :: 3.9
Classifier: Programming Language :: Python :: Implementation :: CPython
Classifier: Programming Language :: Python :: Implementation :: PyPy
Classifier: Topic :: Terminals
Requires-Python: >=2.7
License-File: LICENSE
Requires-Dist: colorama
